latex_test_shuffler/__init__.py
latex_test_shuffler-0.1.4.dist-info/METADATA
latex_test_shuffler-0.1.4.dist-info/WHEEL
latex_test_shuffler-0.1.4.dist-info/entry_points.txt
latex_test_shuffler-0.1.4.dist-info/RECORD
