Metadata-Version: 2.4
Name: latex-test-shuffler
Version: 0.1.4
Summary: LaTeX test shuffler
Author-email: Sergio Barrachina Mir <barrachi@uji.es>
Requires-Python: >=3.11
Requires-Dist: pandas>=2.2.3
Requires-Dist: rich>=13.9.4
Requires-Dist: texsoup>=0.3.1
Requires-Dist: tqdm>=4.67.0
